{
  // The template which will be used for spawn only
  // Example: 
  // {
  //     "name": "default",
  //     "desc": "",
  //     "file": "default.nbt",
  //     "spawns": "default",
  //     "direction": "south",
  //     "offset": [ 0, 0 ]
  // }
  "spawn": {
      "name": "Spawn",
      "desc": "",
      "file": "spawn_island.nbt",
      "spawns": "default",
      "direction": "south"
    },

  "spawns": {
    "default": [
      [ 8, 0, 8 ]
    ]
  },
  
  // The list of templates being available. The first entry is the default template.
  "templates": [
  
{
      "name": "Isolation Chamber",
      "file": "isolated_chamber.nbt",
      "spawns": "default",
      "direction": "south"
    }
  ]
}
